__init__.py
main.py
stubs.py
tkr_nexus_worker-0.1.4.dist-info/METADATA
tkr_nexus_worker-0.1.4.dist-info/WHEEL
tkr_nexus_worker-0.1.4.dist-info/entry_points.txt
tkr_nexus_worker-0.1.4.dist-info/RECORD
