Metadata-Version: 2.4
Name: tkr_nexus_worker
Version: 0.1.4
Summary: A tierkreis worker for interacting with Nexus.
Requires-Python: >=3.12
Requires-Dist: qnexus==0.18.2
Requires-Dist: tierkreis
